{
    "users": ["example"],
    "authorization": {
        "sudo": {
            "users": ["example"],
            "passwordless": "true"
        }
    },
    "mysql": {
        "server_root_password": "examplepassword",
        "server_repl_password": "examplepassword",
        "server_debian_password": "examplepassword"
    },
    "run_list": [
        "recipe[user::data_bag]",
        "recipe[drupal::drupal-project]",
        "recipe[drupal::default]",
        "recipe[drupal::development]",
        "recipe[drupal::drush]"
        /*"role[spec-low]"*/
    ]
}
